unmatch/__init__.py
unmatch/test.py
unmatch/ungreat_matching.py
unmatch-1.2.1.dist-info/LICENSE
unmatch-1.2.1.dist-info/METADATA
unmatch-1.2.1.dist-info/WHEEL
unmatch-1.2.1.dist-info/top_level.txt
unmatch-1.2.1.dist-info/RECORD
