Metadata-Version: 2.1
Name: unmatch
Version: 1.2.1
Summary: ungreat matching of strings module
Home-page: https://github.com/FallenNephalem/ungreat_matching
Author: Fallen Nephalem
Author-email: ldr200@mail.ru
License: MIT
Classifier: Programming Language :: Python :: 3
Classifier: License :: OSI Approved :: MIT License
Classifier: Operating System :: OS Independent
Requires-Python: >=3.6
License-File: LICENSE
